{
  "version": 1,
  "updated_at": "2026-05-03T00:00:00Z",
  "hierarchy": {
    "electronic": [
      "house",
      "techno",
      "trance",
      "drum and bass",
      "dubstep",
      "edm",
      "electro",
      "ambient",
      "idm",
      "downtempo",
      "breakbeat",
      "glitch",
      "hardcore",
      "industrial",
      "minimal",
      "synthpop",
      "trip hop",
      "garage",
      "jungle",
      "acid"
    ],
    "rock": [
      "alternative rock",
      "punk",
      "metal",
      "grunge",
      "indie rock",
      "blues rock",
      "folk rock",
      "psychedelic rock",
      "hard rock",
      "classic rock",
      "progressive rock",
      "post punk",
      "shoegaze",
      "emo",
      "ska"
    ],
    "hip_hop": [
      "hip hop",
      "trap",
      "drill",
      "boom bap",
      "gangsta",
      "crunk",
      "conscious",
      "phonk",
      "mumble",
      "uk hip hop",
      "west coast",
      "east coast",
      "southern",
      "alternative hip hop",
      "experimental"
    ],
    "pop": [
      "pop",
      "synthpop",
      "indie pop",
      "dance pop",
      "electropop",
      "teen pop",
      "bubblegum pop",
      "latin pop",
      "art pop",
      "chamber pop",
      "dream pop",
      "hyperpop",
      "art",
      "progressive pop",
      "country pop"
    ],
    "latin": [
      "salsa",
      "reggaeton",
      "cumbia",
      "bachata",
      "merengue",
      "samba",
      "bossa nova",
      "forro",
      "pagode",
      "axe",
      "flamenco",
      "tango",
      "mariachi",
      "norteño",
      "vallenato"
    ]
  }
}
